Metadata-Version: 2.0
Name: odoo9-addon-sale-procurement-group-by-line
Version: 9.0.1.0.0
Summary: Base module for multiple procurement group by Sale order
Home-page: https://github.com/OCA/sale-workflow
Author: Camptocamp,Eficent,Serpent,Odoo Community Association (OCA)
Author-email: support@odoo-community.org
License: AGPL-3
Platform: UNKNOWN
Requires-Dist: odoo (<9.1a,>=9.0a)
Classifier: Programming Language :: Python :: 2.7
Classifier: Framework :: Odoo
Classifier: License :: OSI Approved :: GNU Affero General Public License v3
